ChimuApi/__init__.py
ChimuApi/chimu_api.py
ChimuApi/classes.py
ChimuApi-0.1.5.dist-info/LICENSE
ChimuApi-0.1.5.dist-info/METADATA
ChimuApi-0.1.5.dist-info/WHEEL
ChimuApi-0.1.5.dist-info/top_level.txt
ChimuApi-0.1.5.dist-info/RECORD
