Metadata-Version: 2.1
Name: ChimuApi
Version: 0.1.5
Summary: API Wrapper around Chimu.moe API for both synchronous and asynchronous purposes.
Home-page: https://github.com/lenforiee/ChimuApi
Author: Lenforiee
Author-email: lenforiee@misumi.me
License: UNKNOWN
Platform: UNKNOWN
Classifier: Programming Language :: Python :: 3
Classifier: License :: OSI Approved :: MIT License
Classifier: Operating System :: OS Independent
Requires-Python: >=3.6
